Workbook

Sheet Datasets
A1: Age | B1: Attrition | C1: Business_Travel | D1: Daily_Rate | E1: Department | F1: DistanceFromHome | G1: Education | H1: EducationField | I1: EmployeeCount | J1: EmployeeNumber | K1: EnvironmentSatisfaction | L1: Demographic Insights | M1: HourlyRate | N1: JobInvolvement | O1: JobLevel | P1: JobRole | Q1: JobSatisfaction | R1: MaritalStatus | S1: MonthlyIncome | T1: MonthlyRate | U1: NumCompaniesWorked | V1: Over18 | W1: OverTime | X1: PercentSalaryHike | Y1: PerformanceRating | Z1: RelationshipSatisfaction | AA1: StandardHours | AB1: StockOptionLevel | AC1: TotalWorkingYears | AD1: TrainingTimesLastYear | AE1: WorkLifeBalance | AF1: YearsAtCompany | AG1: YearsInCurrentRole | AH1: YearsSinceLastPromotion | AI1: YearsWithCurrManager
A2: 20 | B2: Yes | C2: Travel_Rarely | D2: 1362 | E2: Research & Development | F2: 10 | G2: 1 | H2: Medical | I2: 1 | J2: 701 | K2: 4 | L2: Male | M2: 32 | N2: 3 | O2: 1 | P2: Research Scientist | Q2: 3 | R2: Single | S2: 1009 | T2: 26999 | U2: 1 | V2: Y | W2: Yes | X2: 11 | Y2: 3 | Z2: 4 | AA2: 80 | AB2: 0 | AC2: 1 | AD2: 5 | AE2: 3 | AF2: 1 | AG2: 0 | AH2: 1 | AI2: 1
A3: 18 | B3: No | C3: Non-Travel | D3: 287 | E3: Research & Development | F3: 5 | G3: 2 | H3: Life Sciences | I3: 1 | J3: 1012 | K3: 2 | L3: Male | M3: 73 | N3: 3 | O3: 1 | P3: Research Scientist | Q3: 4 | R3: Single | S3: 1051 | T3: 13493 | U3: 1 | V3: Y | W3: No | X3: 15 | Y3: 3 | Z3: 4 | AA3: 80 | AB3: 0 | AC3: 0 | AD3: 2 | AE3: 3 | AF3: 0 | AG3: 0 | AH3: 0 | AI3: 0
A4: 28 | B4: No | C4: Travel_Rarely | D4: 1144 | E4: Sales | F4: 10 | G4: 1 | H4: Medical | I4: 1 | J4: 1056 | K4: 4 | L4: Male | M4: 74 | N4: 3 | O4: 1 | P4: Sales Representative | Q4: 2 | R4: Married | S4: 1052 | T4: 23384 | U4: 1 | V4: Y | W4: No | X4: 22 | Y4: 4 | Z4: 2 | AA4: 80 | AB4: 0 | AC4: 1 | AD4: 5 | AE4: 3 | AF4: 1 | AG4: 0 | AH4: 0 | AI4: 0
A5: 30 | B5: Yes | C5: Travel_Rarely | D5: 945 | E5: Sales | F5: 9 | G5: 3 | H5: Medical | I5: 1 | J5: 1876 | K5: 2 | L5: Male | M5: 89 | N5: 3 | O5: 1 | P5: Sales Representative | Q5: 4 | R5: Single | S5: 1081 | T5: 16019 | U5: 1 | V5: Y | W5: No | X5: 13 | Y5: 3 | Z5: 3 | AA5: 80 | AB5: 0 | AC5: 1 | AD5: 3 | AE5: 2 | AF5: 1 | AG5: 0 | AH5: 0 | AI5: 0
A6: 29 | B6: Yes | C6: Travel_Frequently | D6: 746 | E6: Sales | F6: 24 | G6: 3 | H6: Technical Degree | I6: 1 | J6: 1928 | K6: 3 | L6: Male | M6: 45 | N6: 4 | O6: 1 | P6: Sales Representative | Q6: 1 | R6: Single | S6: 1091 | T6: 10642 | U6: 1 | V6: Y | W6: No | X6: 17 | Y6: 3 | Z6: 4 | AA6: 80 | AB6: 0 | AC6: 1 | AD6: 3 | AE6: 3 | AF6: 1 | AG6: 0 | AH6: 0 | AI6: 0
A7: 19 | B7: Yes | C7: Travel_Rarely | D7: 303 | E7: Research & Development | F7: 2 | G7: 3 | H7: Life Sciences | I7: 1 | J7: 243 | K7: 2 | L7: Male | M7: 47 | N7: 2 | O7: 1 | P7: Laboratory Technician | Q7: 4 | R7: Single | S7: 1102 | T7: 9241 | U7: 1 | V7: Y | W7: No | X7: 22 | Y7: 4 | Z7: 3 | AA7: 80 | AB7: 0 | AC7: 1 | AD7: 3 | AE7: 2 | AF7: 1 | AG7: 0 | AH7: 1 | AI7: 0
A8: 25 | B8: Yes | C8: Travel_Frequently | D8: 599 | E8: Sales | F8: 24 | G8: 1 | H8: Life Sciences | I8: 1 | J8: 1273 | K8: 3 | L8: Male | M8: 73 | N8: 1 | O8: 1 | P8: Sales Representative | Q8: 4 | R8: Single | S8: 1118 | T8: 8040 | U8: 1 | V8: Y | W8: Yes | X8: 14 | Y8: 3 | Z8: 4 | AA8: 80 | AB8: 0 | AC8: 1 | AD8: 4 | AE8: 3 | AF8: 1 | AG8: 0 | AH8: 1 | AI8: 0
A9: 31 | B9: No | C9: Travel_Rarely | D9: 1276 | E9: Research & Development | F9: 2 | G9: 1 | H9: Medical | I9: 1 | J9: 1974 | K9: 4 | L9: Female | M9: 59 | N9: 1 | O9: 1 | P9: Laboratory Technician | Q9: 4 | R9: Divorced | S9: 1129 | T9: 17536 | U9: 1 | V9: Y | W9: Yes | X9: 11 | Y9: 3 | Z9: 3 | AA9: 80 | AB9: 3 | AC9: 1 | AD9: 4 | AE9: 3 | AF9: 1 | AG9: 0 | AH9: 0 | AI9: 0
A10: 18 | B10: No | C10: Travel_Rarely | D10: 812 | E10: Sales | F10: 10 | G10: 3 | H10: Medical | I10: 1 | J10: 411 | K10: 4 | L10: Female | M10: 69 | N10: 2 | O10: 1 | P10: Sales Representative | Q10: 3 | R10: Single | S10: 1200 | T10: 9724 | U10: 1 | V10: Y | W10: No | X10: 12 | Y10: 3 | Z10: 1 | AA10: 80 | AB10: 0 | AC10: 0 | AD10: 2 | AE10: 3 | AF10: 0 | AG10: 0 | AH10: 0 | AI10: 0
A11: 23 | B11: No | C11: Travel_Rarely | D11: 373 | E11: Research & Development | F11: 1 | G11: 2 | H11: Life Sciences | I11: 1 | J11: 1270 | K11: 4 | L11: Male | M11: 47 | N11: 3 | O11: 1 | P11: Research Scientist | Q11: 3 | R11: Married | S11: 1223 | T11: 16901 | U11: 1 | V11: Y | W11: No | X11: 22 | Y11: 4 | Z11: 4 | AA11: 80 | AB11: 1 | AC11: 1 | AD11: 2 | AE11: 3 | AF11: 1 | AG11: 0 | AH11: 0 | AI11: 1
A12: 21 | B12: No | C12: Travel_Rarely | D12: 391 | E12: Research & Development | F12: 15 | G12: 2 | H12: Life Sciences | I12: 1 | J12: 30 | K12: 3 | L12: Male | M12: 96 | N12: 3 | O12: 1 | P12: Research Scientist | Q12: 4 | R12: Single | S12: 1232 | T12: 19281 | U12: 1 | V12: Y | W12: No | X12: 14 | Y12: 3 | Z12: 4 | AA12: 80 | AB12: 0 | AC12: 0 | AD12: 6 | AE12: 3 | AF12: 0 | AG12: 0 | AH12: 0 | AI12: 0
A13: 31 | B13: Yes | C13: Travel_Rarely | D13: 202 | E13: Research & Development | F13: 8 | G13: 3 | H13: Life Sciences | I13: 1 | J13: 1433 | K13: 1 | L13: Female | M13: 34 | N13: 2 | O13: 1 | P13: Research Scientist | Q13: 2 | R13: Single | S13: 1261 | T13: 22262 | U13: 1 | V13: Y | W13: No | X13: 12 | Y13: 3 | Z13: 3 | AA13: 80 | AB13: 0 | AC13: 1 | AD13: 3 | AE13: 4 | AF13: 1 | AG13: 0 | AH13: 0 | AI13: 0
... A1471: 52 | B1471: No | C1471: Travel_Rarely | D1471: 699 | E1471: Research & Development | F1471: 1 | G1471: 4 | H1471: Life Sciences | I1471: 1 | J1471: 259 | K1471: 3 | L1471: Male | M1471: 65 | N1471: 2 | O1471: 5 | P1471: Manager | Q1471: 3 | R1471: Married | S1471: 19999 | T1471: 5678 | U1471: 0 | V1471: Y | W1471: No | X1471: 14 | Y1471: 3 | Z1471: 1 | AA1471: 80 | AB1471: 1 | AC1471: 34 | AD1471: 5 | AE1471: 3 | AF1471: 33 | AG1471: 18 | AH1471: 11 | AI1471: 9
B1473: =COUNTIF(Table1[Attrition],"Yes") -> 237 | I1473: =COUNT(Table1[EmployeeCount]) -> 1470

Sheet  Data Understanding
A2: Data understanding using formulas | J2: Attrition Analysis
J4: Research & Development shows the highest attrition, suggesting potential challenges related to workload, role expectations, or career growth within technical teams.
A5: total employees | C5: total employees left
A6: =COUNT(Table1[EmployeeCount]) -> 1470 | C6: =COUNTIF(Table1[Attrition],"Yes") -> 237 | E6: =COUNTA(Table1[Attrition]) -> 1470 | F6: =COUNTA(Datasets!B2:B1463) -> 1462
A8: overall Attrition Rate
A9: =Datasets!B1473/Datasets!I1473 -> 0.16122449
A10: The organization has an overall attrition rate of approximately 16% | J10: Department | K10: Attrition Count | N10: Over time | O10: =K10 -> Attrition Count
J11: Sales | K11: =COUNTIFS(Table1[Department],' Data Understanding'!J11,Table1[Attrition],"Yes") -> 92 | N11: Yes | O11: =COUNTIFS(Table1[Attrition],"Yes",Table1[OverTime],Datasets!W1452) -> 110
J12: Research & Development | K12: =COUNTIFS(Table1[Department],' Data Understanding'!J12,Table1[Attrition],"Yes") -> 133 | N12: No | O12: =COUNTIFS(Table1[Attrition],"Yes",Table1[OverTime],Datasets!W3) -> 110
J13: Human Resources | K13: =COUNTIFS(Table1[Department],' Data Understanding'!J13,Table1[Attrition],"Yes") -> 12

Sheet Demographic Insights
A1: Demographic Insights
A3: Male employees exhibit a higher attrition rate compared to female employees | E3: Age | F3: Helper column | J3: Attrition is highest among employees under 30, indicating early career employees are more likely to leave, while attrition decreases with age and experience.
E4: 20 | F4: {=_xlfn.IFS(E4<30,"Under",E4<40,"between",E4>=40,"plus")} -> Under
E5: 18 | F5: {=_xlfn.IFS(E5<30,"Under",E5<40,"between",E5>=40,"plus")} -> Under
A6: MALE | B6: FEMALE | E6: 28 | F6: {=_xlfn.IFS(E6<30,"Under",E6<40,"between",E6>=40,"plus")} -> Under
A7: =COUNTIFS(Table1[Demographic Insights],"Male",Table1[Attrition],"Yes") -> 150 | B7: =COUNTIFS(Table1[Demographic Insights],"Female",Table1[Attrition],"Yes") -> 87 | E7: 30 | F7: {=_xlfn.IFS(E7<30,"Under",E7<40,"between",E7>=40,"plus")} -> between | G7: Age group | H7: Attrition count
E8: 29 | F8: {=_xlfn.IFS(E8<30,"Under",E8<40,"between",E8>=40,"plus")} -> Under | G8: <30 | H8: =COUNTIFS(F4:F1473,"Under",Table1[Attrition],"Yes") -> 91
E9: 19 | F9: {=_xlfn.IFS(E9<30,"Under",E9<40,"between",E9>=40,"plus")} -> Under | G9: 30-40 | H9: =COUNTIFS('Demographic Insights'!F4:F1473,"between",Table1[Attrition],"Yes") -> 89
E10: 25 | F10: {=_xlfn.IFS(E10<30,"Under",E10<40,"between",E10>=40,"plus")} -> Under | G10: 40+ | H10: =COUNTIFS(F4:F1473,"plus",Table1[Attrition],"Yes") -> 57
E11: 31 | F11: {=_xlfn.IFS(E11<30,"Under",E11<40,"between",E11>=40,"plus")} -> between
E12: 18 | F12: {=_xlfn.IFS(E12<30,"Under",E12<40,"between",E12>=40,"plus")} -> Under
E13: 23 | F13: {=_xlfn.IFS(E13<30,"Under",E13<40,"between",E13>=40,"plus")} -> Under
E14: 21 | F14: {=_xlfn.IFS(E14<30,"Under",E14<40,"between",E14>=40,"plus")} -> Under
E15: 31 | F15: {=_xlfn.IFS(E15<30,"Under",E15<40,"between",E15>=40,"plus")} -> between
E16: 30 | F16: {=_xlfn.IFS(E16<30,"Under",E16<40,"between",E16>=40,"plus")} -> between
E17: 35 | F17: {=_xlfn.IFS(E17<30,"Under",E17<40,"between",E17>=40,"plus")} -> between
E18: 31 | F18: {=_xlfn.IFS(E18<30,"Under",E18<40,"between",E18>=40,"plus")} -> between
E19: 32 | F19: {=_xlfn.IFS(E19<30,"Under",E19<40,"between",E19>=40,"plus")} -> between
E20: 21 | F20: {=_xlfn.IFS(E20<30,"Under",E20<40,"between",E20>=40,"plus")} -> Under
E21: 18 | F21: {=_xlfn.IFS(E21<30,"Under",E21<40,"between",E21>=40,"plus")} -> Under
E22: 19 | F22: {=_xlfn.IFS(E22<30,"Under",E22<40,"between",E22>=40,"plus")} -> Under
... E1473: 52 | F1473: {=_xlfn.IFS(E1473<30,"Under",E1473<40,"between",E1473>=40,"plus")} -> plus

Sheet Job Satisfaction & Work-Life Ba
C1: Job Satisfaction & Work-Life Balance | H1: WorkLifeBalance
A2: 3 | B2: {=_xlfn.IFS(Datasets!Q2=1,"LoW",Table1[[#This Row],[JobSatisfaction]]=2,"Medium",Table1[[#This Row],[JobSatisfaction]]=3,"High",Table1[[#This Row],[JobSatisfaction]]=4,"Very High")} -> High | H2: 3 | I2: {=_xlfn.IFS(H2=1,"low",H2=2,"medium",H2=3,"balanced",H2=4,"Good")} -> balanced
A3: 4 | B3: {=_xlfn.IFS(Datasets!Q3=1,"LoW",Table1[[#This Row],[JobSatisfaction]]=2,"Medium",Table1[[#This Row],[JobSatisfaction]]=3,"High",Table1[[#This Row],[JobSatisfaction]]=4,"Very High")} -> Very High | H3: 3 | I3: {=_xlfn.IFS(H3=1,"low",H3=2,"medium",H3=3,"balanced",H3=4,"Good")} -> balanced
A4: 2 | B4: {=_xlfn.IFS(Datasets!Q4=1,"LoW",Table1[[#This Row],[JobSatisfaction]]=2,"Medium",Table1[[#This Row],[JobSatisfaction]]=3,"High",Table1[[#This Row],[JobSatisfaction]]=4,"Very High")} -> Medium | H4: 3 | I4: {=_xlfn.IFS(H4=1,"low",H4=2,"medium",H4=3,"balanced",H4=4,"Good")} -> balanced
A5: 4 | B5: {=_xlfn.IFS(Datasets!Q5=1,"LoW",Table1[[#This Row],[JobSatisfaction]]=2,"Medium",Table1[[#This Row],[JobSatisfaction]]=3,"High",Table1[[#This Row],[JobSatisfaction]]=4,"Very High")} -> Very High | H5: 2 | I5: {=_xlfn.IFS(H5=1,"low",H5=2,"medium",H5=3,"balanced",H5=4,"Good")} -> medium | L5: Work life levels | M5: Attrition Count
A6: 1 | B6: {=_xlfn.IFS(Datasets!Q6=1,"LoW",Table1[[#This Row],[JobSatisfaction]]=2,"Medium",Table1[[#This Row],[JobSatisfaction]]=3,"High",Table1[[#This Row],[JobSatisfaction]]=4,"Very High")} -> LoW | E6: Satisfaction Level | F6: Attrition Count | H6: 3 | I6: {=_xlfn.IFS(H6=1,"low",H6=2,"medium",H6=3,"balanced",H6=4,"Good")} -> balanced | L6: Low | M6: =COUNTIFS(I2:I1471,"low",Table1[Attrition],"Yes") -> 25
A7: 4 | B7: {=_xlfn.IFS(Datasets!Q7=1,"LoW",Table1[[#This Row],[JobSatisfaction]]=2,"Medium",Table1[[#This Row],[JobSatisfaction]]=3,"High",Table1[[#This Row],[JobSatisfaction]]=4,"Very High")} -> Very High | E7: Low | F7: =COUNTIFS(B2:B1471,"LoW",Table1[Attrition],"Yes") -> 66 | H7: 2 | I7: {=_xlfn.IFS(H7=1,"low",H7=2,"medium",H7=3,"balanced",H7=4,"Good")} -> medium | L7: Medium | M7: =COUNTIFS(I2:I1471,"medium",Table1[Attrition],"Yes") -> 58
A8: 4 | B8: {=_xlfn.IFS(Datasets!Q8=1,"LoW",Table1[[#This Row],[JobSatisfaction]]=2,"Medium",Table1[[#This Row],[JobSatisfaction]]=3,"High",Table1[[#This Row],[JobSatisfaction]]=4,"Very High")} -> Very High | E8: Medium | F8: =COUNTIFS(B3:B1472,"Medium",Table1[Attrition],"Yes") -> 53 | H8: 3 | I8: {=_xlfn.IFS(H8=1,"low",H8=2,"medium",H8=3,"balanced",H8=4,"Good")} -> balanced | L8: Balanced | M8: =COUNTIFS(I2:I1471,"balanced",Table1[Attrition],"Yes") -> 127
A9: 4 | B9: {=_xlfn.IFS(Datasets!Q9=1,"LoW",Table1[[#This Row],[JobSatisfaction]]=2,"Medium",Table1[[#This Row],[JobSatisfaction]]=3,"High",Table1[[#This Row],[JobSatisfaction]]=4,"Very High")} -> Very High | E9: High | F9: =COUNTIFS(B4:B1473,"High",Table1[Attrition],"Yes") -> 75 | H9: 3 | I9: {=_xlfn.IFS(H9=1,"low",H9=2,"medium",H9=3,"balanced",H9=4,"Good")} -> balanced | L9: Good | M9: =COUNTIFS(I2:I1471,"Good",Table1[Attrition],"Yes") -> 27
A10: 3 | B10: {=_xlfn.IFS(Datasets!Q10=1,"LoW",Table1[[#This Row],[JobSatisfaction]]=2,"Medium",Table1[[#This Row],[JobSatisfaction]]=3,"High",Table1[[#This Row],[JobSatisfaction]]=4,"Very High")} -> High | E10: Very High | F10: =COUNTIFS(B5:B1474,"Very High",Table1[Attrition],"Yes") -> 72 | H10: 3 | I10: {=_xlfn.IFS(H10=1,"low",H10=2,"medium",H10=3,"balanced",H10=4,"Good")} -> balanced
A11: 3 | B11: {=_xlfn.IFS(Datasets!Q11=1,"LoW",Table1[[#This Row],[JobSatisfaction]]=2,"Medium",Table1[[#This Row],[JobSatisfaction]]=3,"High",Table1[[#This Row],[JobSatisfaction]]=4,"Very High")} -> High | H11: 3 | I11: {=_xlfn.IFS(H11=1,"low",H11=2,"medium",H11=3,"balanced",H11=4,"Good")} -> balanced
A12: 4 | B12: {=_xlfn.IFS(Datasets!Q12=1,"LoW",Table1[[#This Row],[JobSatisfaction]]=2,"Medium",Table1[[#This Row],[JobSatisfaction]]=3,"High",Table1[[#This Row],[JobSatisfaction]]=4,"Very High")} -> Very High | H12: 3 | I12: {=_xlfn.IFS(H12=1,"low",H12=2,"medium",H12=3,"balanced",H12=4,"Good")} -> balanced
A13: 2 | B13: {=_xlfn.IFS(Datasets!Q13=1,"LoW",Table1[[#This Row],[JobSatisfaction]]=2,"Medium",Table1[[#This Row],[JobSatisfaction]]=3,"High",Table1[[#This Row],[JobSatisfaction]]=4,"Very High")} -> Medium | H13: 4 | I13: {=_xlfn.IFS(H13=1,"low",H13=2,"medium",H13=3,"balanced",H13=4,"Good")} -> Good
A14: 3 | B14: {=_xlfn.IFS(Datasets!Q14=1,"LoW",Table1[[#This Row],[JobSatisfaction]]=2,"Medium",Table1[[#This Row],[JobSatisfaction]]=3,"High",Table1[[#This Row],[JobSatisfaction]]=4,"Very High")} -> High | H14: 2 | I14: {=_xlfn.IFS(H14=1,"low",H14=2,"medium",H14=3,"balanced",H14=4,"Good")} -> medium
A15: 3 | B15: {=_xlfn.IFS(Datasets!Q15=1,"LoW",Table1[[#This Row],[JobSatisfaction]]=2,"Medium",Table1[[#This Row],[JobSatisfaction]]=3,"High",Table1[[#This Row],[JobSatisfaction]]=4,"Very High")} -> High | H15: 3 | I15: {=_xlfn.IFS(H15=1,"low",H15=2,"medium",H15=3,"balanced",H15=4,"Good")} -> balanced | L15: Attrition is not limited to low satisfaction levels, as employees with high and very high job satisfaction also show notable attrition, indicating external factors beyond satisfaction may influence turnover.
A16: 3 | B16: {=_xlfn.IFS(Datasets!Q16=1,"LoW",Table1[[#This Row],[JobSatisfaction]]=2,"Medium",Table1[[#This Row],[JobSatisfaction]]=3,"High",Table1[[#This Row],[JobSatisfaction]]=4,"Very High")} -> High | H16: 3 | I16: {=_xlfn.IFS(H16=1,"low",H16=2,"medium",H16=3,"balanced",H16=4,"Good")} -> balanced
A17: 2 | B17: {=_xlfn.IFS(Datasets!Q17=1,"LoW",Table1[[#This Row],[JobSatisfaction]]=2,"Medium",Table1[[#This Row],[JobSatisfaction]]=3,"High",Table1[[#This Row],[JobSatisfaction]]=4,"Very High")} -> Medium | H17: 3 | I17: {=_xlfn.IFS(H17=1,"low",H17=2,"medium",H17=3,"balanced",H17=4,"Good")} -> balanced
A18: 1 | B18: {=_xlfn.IFS(Datasets!Q18=1,"LoW",Table1[[#This Row],[JobSatisfaction]]=2,"Medium",Table1[[#This Row],[JobSatisfaction]]=3,"High",Table1[[#This Row],[JobSatisfaction]]=4,"Very High")} -> LoW | H18: 2 | I18: {=_xlfn.IFS(H18=1,"low",H18=2,"medium",H18=3,"balanced",H18=4,"Good")} -> medium
A19: 3 | B19: {=_xlfn.IFS(Datasets!Q19=1,"LoW",Table1[[#This Row],[JobSatisfaction]]=2,"Medium",Table1[[#This Row],[JobSatisfaction]]=3,"High",Table1[[#This Row],[JobSatisfaction]]=4,"Very High")} -> High | H19: 3 | I19: {=_xlfn.IFS(H19=1,"low",H19=2,"medium",H19=3,"balanced",H19=4,"Good")} -> balanced
A20: 2 | B20: {=_xlfn.IFS(Datasets!Q20=1,"LoW",Table1[[#This Row],[JobSatisfaction]]=2,"Medium",Table1[[#This Row],[JobSatisfaction]]=3,"High",Table1[[#This Row],[JobSatisfaction]]=4,"Very High")} -> Medium | H20: 3 | I20: {=_xlfn.IFS(H20=1,"low",H20=2,"medium",H20=3,"balanced",H20=4,"Good")} -> balanced
A21: 3 | B21: {=_xlfn.IFS(Datasets!Q21=1,"LoW",Table1[[#This Row],[JobSatisfaction]]=2,"Medium",Table1[[#This Row],[JobSatisfaction]]=3,"High",Table1[[#This Row],[JobSatisfaction]]=4,"Very High")} -> High | H21: 1 | I21: {=_xlfn.IFS(H21=1,"low",H21=2,"medium",H21=3,"balanced",H21=4,"Good")} -> low
A22: 3 | B22: {=_xlfn.IFS(Datasets!Q22=1,"LoW",Table1[[#This Row],[JobSatisfaction]]=2,"Medium",Table1[[#This Row],[JobSatisfaction]]=3,"High",Table1[[#This Row],[JobSatisfaction]]=4,"Very High")} -> High | H22: 3 | I22: {=_xlfn.IFS(H22=1,"low",H22=2,"medium",H22=3,"balanced",H22=4,"Good")} -> balanced
A23: 3 | B23: {=_xlfn.IFS(Datasets!Q23=1,"LoW",Table1[[#This Row],[JobSatisfaction]]=2,"Medium",Table1[[#This Row],[JobSatisfaction]]=3,"High",Table1[[#This Row],[JobSatisfaction]]=4,"Very High")} -> High | H23: 1 | I23: {=_xlfn.IFS(H23=1,"low",H23=2,"medium",H23=3,"balanced",H23=4,"Good")} -> low
A24: 4 | B24: {=_xlfn.IFS(Datasets!Q24=1,"LoW",Table1[[#This Row],[JobSatisfaction]]=2,"Medium",Table1[[#This Row],[JobSatisfaction]]=3,"High",Table1[[#This Row],[JobSatisfaction]]=4,"Very High")} -> Very High | H24: 4 | I24: {=_xlfn.IFS(H24=1,"low",H24=2,"medium",H24=3,"balanced",H24=4,"Good")} -> Good
A25: 1 | B25: {=_xlfn.IFS(Datasets!Q25=1,"LoW",Table1[[#This Row],[JobSatisfaction]]=2,"Medium",Table1[[#This Row],[JobSatisfaction]]=3,"High",Table1[[#This Row],[JobSatisfaction]]=4,"Very High")} -> LoW | H25: 3 | I25: {=_xlfn.IFS(H25=1,"low",H25=2,"medium",H25=3,"balanced",H25=4,"Good")} -> balanced
A26: 4 | B26: {=_xlfn.IFS(Datasets!Q26=1,"LoW",Table1[[#This Row],[JobSatisfaction]]=2,"Medium",Table1[[#This Row],[JobSatisfaction]]=3,"High",Table1[[#This Row],[JobSatisfaction]]=4,"Very High")} -> Very High | H26: 4 | I26: {=_xlfn.IFS(H26=1,"low",H26=2,"medium",H26=3,"balanced",H26=4,"Good")} -> Good
A27: 3 | B27: {=_xlfn.IFS(Datasets!Q27=1,"LoW",Table1[[#This Row],[JobSatisfaction]]=2,"Medium",Table1[[#This Row],[JobSatisfaction]]=3,"High",Table1[[#This Row],[JobSatisfaction]]=4,"Very High")} -> High | H27: 2 | I27: {=_xlfn.IFS(H27=1,"low",H27=2,"medium",H27=3,"balanced",H27=4,"Good")} -> medium
... A1471: 3 | B1471: {=_xlfn.IFS(Datasets!Q1471=1,"LoW",Table1[[#This Row],[JobSatisfaction]]=2,"Medium",Table1[[#This Row],[JobSatisfaction]]=3,"High",Table1[[#This Row],[JobSatisfaction]]=4,"Very High")} -> High | H1471: 3 | I1471: {=_xlfn.IFS(H1471=1,"low",H1471=2,"medium",H1471=3,"balanced",H1471=4,"Good")} -> balanced

Sheet  Salary & Experience Impact
E1: Salary & Experience Impact
A3: MonthlyIncome | B3: helper column | G3: years of exp | H3: =B3 -> helper column
G4: 1 | H4: {=_xlfn.IFS(G4<=15,"Junior",G4<=30,"Mid level",G4>30,"Lead")} -> Junior
A5: 1009 | B5: {=_xlfn.IFS(A5<=8000,"low",A5<15000,"medium",A5>=15000,"high")} -> low | G5: 0 | H5: {=_xlfn.IFS(G5<=15,"Junior",G5<=30,"Mid level",G5>30,"Lead")} -> Junior | J5: Exp by group | K5: Attrition Count
A6: 1051 | B6: {=_xlfn.IFS(A6<=8000,"low",A6<15000,"medium",A6>=15000,"high")} -> low | G6: 1 | H6: {=_xlfn.IFS(G6<=15,"Junior",G6<=30,"Mid level",G6>30,"Lead")} -> Junior | J6: junior | K6: =COUNTIFS(H4:H1473,J6,Table1[Attrition],"Yes") -> 224
A7: 1052 | B7: {=_xlfn.IFS(A7<=8000,"low",A7<15000,"medium",A7>=15000,"high")} -> low | D7: IncomeGroup | E7: AttritionCount | G7: 1 | H7: {=_xlfn.IFS(G7<=15,"Junior",G7<=30,"Mid level",G7>30,"Lead")} -> Junior | J7: mid level | K7: =COUNTIFS(H5:H1474,J7,Table1[Attrition],"Yes") -> 11
A8: 1081 | B8: {=_xlfn.IFS(A8<=8000,"low",A8<15000,"medium",A8>=15000,"high")} -> low | D8: low | E8: =COUNTIFS(B5:B1474,D8,Table1[Attrition],"Yes") -> 197 | G8: 1 | H8: {=_xlfn.IFS(G8<=15,"Junior",G8<=30,"Mid level",G8>30,"Lead")} -> Junior | J8: lead | K8: =COUNTIFS(H6:H1475,J8,Table1[Attrition],"Yes") -> 2
A9: 1091 | B9: {=_xlfn.IFS(A9<=8000,"low",A9<15000,"medium",A9>=15000,"high")} -> low | D9: medium | E9: =COUNTIFS(B6:B1475,D9,Table1[Attrition],"Yes") -> 35 | G9: 1 | H9: {=_xlfn.IFS(G9<=15,"Junior",G9<=30,"Mid level",G9>30,"Lead")} -> Junior
A10: 1102 | B10: {=_xlfn.IFS(A10<=8000,"low",A10<15000,"medium",A10>=15000,"high")} -> low | D10: high | E10: =COUNTIFS(B7:B1476,D10,Table1[Attrition],"Yes") -> 5 | G10: 1 | H10: {=_xlfn.IFS(G10<=15,"Junior",G10<=30,"Mid level",G10>30,"Lead")} -> Junior
A11: 1118 | B11: {=_xlfn.IFS(A11<=8000,"low",A11<15000,"medium",A11>=15000,"high")} -> low | G11: 1 | H11: {=_xlfn.IFS(G11<=15,"Junior",G11<=30,"Mid level",G11>30,"Lead")} -> Junior
A12: 1129 | B12: {=_xlfn.IFS(A12<=8000,"low",A12<15000,"medium",A12>=15000,"high")} -> low | G12: 0 | H12: {=_xlfn.IFS(G12<=15,"Junior",G12<=30,"Mid level",G12>30,"Lead")} -> Junior
A13: 1200 | B13: {=_xlfn.IFS(A13<=8000,"low",A13<15000,"medium",A13>=15000,"high")} -> low | G13: 1 | H13: {=_xlfn.IFS(G13<=15,"Junior",G13<=30,"Mid level",G13>30,"Lead")} -> Junior | J13: Attrition is heavily concentrated among low income and junior level employees, highlighting compensation and early career support as key areas for retention improvement.
A14: 1223 | B14: {=_xlfn.IFS(A14<=8000,"low",A14<15000,"medium",A14>=15000,"high")} -> low | G14: 0 | H14: {=_xlfn.IFS(G14<=15,"Junior",G14<=30,"Mid level",G14>30,"Lead")} -> Junior
A15: 1232 | B15: {=_xlfn.IFS(A15<=8000,"low",A15<15000,"medium",A15>=15000,"high")} -> low | G15: 1 | H15: {=_xlfn.IFS(G15<=15,"Junior",G15<=30,"Mid level",G15>30,"Lead")} -> Junior
A16: 1261 | B16: {=_xlfn.IFS(A16<=8000,"low",A16<15000,"medium",A16>=15000,"high")} -> low | G16: 1 | H16: {=_xlfn.IFS(G16<=15,"Junior",G16<=30,"Mid level",G16>30,"Lead")} -> Junior
A17: 1274 | B17: {=_xlfn.IFS(A17<=8000,"low",A17<15000,"medium",A17>=15000,"high")} -> low | G17: 1 | H17: {=_xlfn.IFS(G17<=15,"Junior",G17<=30,"Mid level",G17>30,"Lead")} -> Junior
A18: 1281 | B18: {=_xlfn.IFS(A18<=8000,"low",A18<15000,"medium",A18>=15000,"high")} -> low | G18: 1 | H18: {=_xlfn.IFS(G18<=15,"Junior",G18<=30,"Mid level",G18>30,"Lead")} -> Junior
A19: 1359 | B19: {=_xlfn.IFS(A19<=8000,"low",A19<15000,"medium",A19>=15000,"high")} -> low | G19: 1 | H19: {=_xlfn.IFS(G19<=15,"Junior",G19<=30,"Mid level",G19>30,"Lead")} -> Junior
A20: 1393 | B20: {=_xlfn.IFS(A20<=8000,"low",A20<15000,"medium",A20>=15000,"high")} -> low | G20: 1 | H20: {=_xlfn.IFS(G20<=15,"Junior",G20<=30,"Mid level",G20>30,"Lead")} -> Junior
A21: 1416 | B21: {=_xlfn.IFS(A21<=8000,"low",A21<15000,"medium",A21>=15000,"high")} -> low | G21: 0 | H21: {=_xlfn.IFS(G21<=15,"Junior",G21<=30,"Mid level",G21>30,"Lead")} -> Junior
A22: 1420 | B22: {=_xlfn.IFS(A22<=8000,"low",A22<15000,"medium",A22>=15000,"high")} -> low | G22: 1 | H22: {=_xlfn.IFS(G22<=15,"Junior",G22<=30,"Mid level",G22>30,"Lead")} -> Junior
A23: 1483 | B23: {=_xlfn.IFS(A23<=8000,"low",A23<15000,"medium",A23>=15000,"high")} -> low | G23: 0 | H23: {=_xlfn.IFS(G23<=15,"Junior",G23<=30,"Mid level",G23>30,"Lead")} -> Junior
A24: 1514 | B24: {=_xlfn.IFS(A24<=8000,"low",A24<15000,"medium",A24>=15000,"high")} -> low | G24: 1 | H24: {=_xlfn.IFS(G24<=15,"Junior",G24<=30,"Mid level",G24>30,"Lead")} -> Junior
A25: 1555 | B25: {=_xlfn.IFS(A25<=8000,"low",A25<15000,"medium",A25>=15000,"high")} -> low | G25: 1 | H25: {=_xlfn.IFS(G25<=15,"Junior",G25<=30,"Mid level",G25>30,"Lead")} -> Junior
... A1473: 19973 | B1473: {=_xlfn.IFS(A1473<=8000,"low",A1473<15000,"medium",A1473>=15000,"high")} -> high | G1473: 33 | H1473: {=_xlfn.IFS(G1473<=15,"Junior",G1473<=30,"Mid level",G1473>30,"Lead")} -> Lead
A1474: 19999 | B1474: {=_xlfn.IFS(A1474<=8000,"low",A1474<15000,"medium",A1474>=15000,"high")} -> high

Sheet KPIs for Dashboard
A1: KPIs for Dashboard
B4: Total Employees | E4: Employees Left
B6: 1470 | E6: =COUNTIF(Table1[Attrition],"Yes") -> 237
E10: Attrition Rate
E11: =COUNTIF(Table1[Attrition],"Yes") / COUNTA(Table1[EmployeeNumber]) -> 0.16122449
